nose_helper/__init__.py
nose_helper/__version__.py
nose_helper/nox_checks/__init__.py
nose_helper/nox_checks/common.py
nose_helper/nox_checks/version_check.py
nose_helper/nox_checks/config/.pylintrc
nose_helper/nox_checks/config/__init__.py
nose_helper-1.8.0.dist-info/licenses/LICENSE
nose_helper-1.8.0.dist-info/METADATA
nose_helper-1.8.0.dist-info/WHEEL
nose_helper-1.8.0.dist-info/top_level.txt
nose_helper-1.8.0.dist-info/RECORD
