Metadata-Version: 2.4
Name: nose_helper
Version: 1.8.0
Summary: build helper
Author: Seuling N.
License: Apache License 2.0
Requires-Python: >=3.9
License-File: LICENSE
Requires-Dist: coverage~=7.9.2
Requires-Dist: nox~=2025.5.1
Requires-Dist: pyenchant<4.0.0,>=3.2.2
Requires-Dist: pylint-pydantic~=0.3.5
Requires-Dist: pylint~=3.3.7
Requires-Dist: pytest~=8.4.1
Requires-Dist: requests<3.0.0,>=2.31.0
Dynamic: author
Dynamic: description
Dynamic: license
Dynamic: license-file
Dynamic: requires-dist
Dynamic: requires-python
Dynamic: summary
